COPYING.txt
HACKING.txt
README.txt
ez_setup.py
pylint.rc
setup.py
eggs/setuptools-0.6c12dev_r88846-py2.7.egg/EGG-INFO/SOURCES.txt
eggs/setuptools-0.6c12dev_r88846-py2.7.egg/EGG-INFO/dependency_links.txt
eggs/setuptools-0.6c12dev_r88846-py2.7.egg/EGG-INFO/entry_points.txt
eggs/setuptools-0.6c12dev_r88846-py2.7.egg/EGG-INFO/top_level.txt
eggs/zc.buildout-1.5.2-py2.7.egg/README.txt
eggs/zc.buildout-1.5.2-py2.7.egg/EGG-INFO/SOURCES.txt
eggs/zc.buildout-1.5.2-py2.7.egg/EGG-INFO/dependency_links.txt
eggs/zc.buildout-1.5.2-py2.7.egg/EGG-INFO/entry_points.txt
eggs/zc.buildout-1.5.2-py2.7.egg/EGG-INFO/namespace_packages.txt
eggs/zc.buildout-1.5.2-py2.7.egg/EGG-INFO/requires.txt
eggs/zc.buildout-1.5.2-py2.7.egg/EGG-INFO/top_level.txt
eggs/zc.buildout-1.5.2-py2.7.egg/zc/buildout/allowhosts.txt
eggs/zc.buildout-1.5.2-py2.7.egg/zc/buildout/bootstrap.txt
eggs/zc.buildout-1.5.2-py2.7.egg/zc/buildout/buildout.txt
eggs/zc.buildout-1.5.2-py2.7.egg/zc/buildout/debugging.txt
eggs/zc.buildout-1.5.2-py2.7.egg/zc/buildout/dependencylinks.txt
eggs/zc.buildout-1.5.2-py2.7.egg/zc/buildout/distribute.txt
eggs/zc.buildout-1.5.2-py2.7.egg/zc/buildout/download.txt
eggs/zc.buildout-1.5.2-py2.7.egg/zc/buildout/downloadcache.txt
eggs/zc.buildout-1.5.2-py2.7.egg/zc/buildout/easy_install.txt
eggs/zc.buildout-1.5.2-py2.7.egg/zc/buildout/extends-cache.txt
eggs/zc.buildout-1.5.2-py2.7.egg/zc/buildout/repeatable.txt
eggs/zc.buildout-1.5.2-py2.7.egg/zc/buildout/runsetup.txt
eggs/zc.buildout-1.5.2-py2.7.egg/zc/buildout/setup.txt
eggs/zc.buildout-1.5.2-py2.7.egg/zc/buildout/testing.txt
eggs/zc.buildout-1.5.2-py2.7.egg/zc/buildout/testing_bugfix.txt
eggs/zc.buildout-1.5.2-py2.7.egg/zc/buildout/unzip.txt
eggs/zc.buildout-1.5.2-py2.7.egg/zc/buildout/update.txt
eggs/zc.buildout-1.5.2-py2.7.egg/zc/buildout/upgrading_distribute.txt
eggs/zc.buildout-1.5.2-py2.7.egg/zc/buildout/virtualenv.txt
eggs/zc.buildout-1.5.2-py2.7.egg/zc/buildout/windows.txt
src/lazr/__init__.py
src/lazr.json.egg-info/PKG-INFO
src/lazr.json.egg-info/SOURCES.txt
src/lazr.json.egg-info/dependency_links.txt
src/lazr.json.egg-info/namespace_packages.txt
src/lazr.json.egg-info/not-zip-safe
src/lazr.json.egg-info/requires.txt
src/lazr.json.egg-info/top_level.txt
src/lazr/json/NEWS.txt
src/lazr/json/README.txt
src/lazr/json/__init__.py
src/lazr/json/_serialisation.py
src/lazr/json/version.txt
src/lazr/json/docs/__init__.py
src/lazr/json/tests/__init__.py
src/lazr/json/tests/test_docs.py