Metadata-Version: 1.1
Name: lazr.json
Version: 0.2
Summary: JSON serialisation utilities.
Home-page: https://launchpad.net/lazr.json
Author: LAZR Developers
Author-email: lazr-developers@lists.launchpad.net
License: LGPL v3
Download-URL: https://launchpad.net/lazr.json/+download
Platform: UNKNOWN
Classifier: Development Status :: 5 - Production/Stable
Classifier: Intended Audience :: Developers
Classifier: License :: OSI Approved :: GNU Library or Lesser General Public License (LGPL)
Classifier: Operating System :: OS Independent
Classifier: Programming Language :: Python
